{
  "DatabaseSettings": {
    "DBProvider": "postgresql",
    "ConnectionString": "Server=3.110.161.35:5432;Database=academy;User Id=admin;Password=DyEhSCq39gKMxK9tGUSBMZa;Include Error Detail=true;Port=5432;"
    //"DBProvider": "mysql",
    //"ConnectionString": "server=192.168.0.245;database=AICoreArchitecture;userid=root;port=3310;password=DyEhSCq39gKMxK9tGUSBMZa;",
    //need to set "InvariantGlobalization"= false in Digitalnomads.API csproj file for mssql database
    //"DBProvider": "mssql",
    //"ConnectionString": "Server=192.168.0.61;Database=AICoreArchitecture;User Id=sa;Password=pjadmin@123$;Encrypt=True;TrustServerCertificate=True;"
  }
}